{
    "log": {
        "disabled": false,
        "level": "info",
        "timestamp": true
    },
    "experimental": {
        "cache_file": {
            "enabled": true,
            "path": "./cache.db",
            "store_fakeip": true
        },
        "clash_api": {
            "external_controller": "127.0.0.1:9090",
            "external_ui": "ui",
            "default_mode": "Rule"
        }
    },
    "dns": {
        "servers": [
            {
                "tag": "aliDns",
                "type": "https",
                "server": "dns.alidns.com",
                "path": "/dns-query",
                "domain_resolver": "local"
            },
            {
                "tag": "local",
                "type": "udp",
                "server": "223.5.5.5"
            },
            {
                "tag": "proxyDns",
                "type": "https",
                "server": "dns.google",
                "path": "/dns-query",
				"domain_resolver": "aliDns",
                "detour": "proxy"
            },
		{
        "type": "fakeip",
        "tag": "fakeip",
        "inet4_range": "198.18.0.0/15",
        "inet6_range": "fc00::/18"
      }
        ],
        "rules": [	
            {
                "rule_set": "geosite-cn",
                "server": "aliDns"
            },
            {
                "clash_mode": "Direct",
                "server": "local"
            },
            {
                "clash_mode": "Global",
                "server": "proxyDns"
            },
			      {
        "query_type": [
          "A",
          "AAAA"
        ],
        "server": "fakeip"
      }
        ],
        "final": "proxyDns",
        "strategy": "prefer_ipv4",
        "independent_cache": true
    },
    "inbounds": [
        {
            "type": "tun",
            "tag": "tun-in",
            "address": [
                "172.19.0.1/30",
                "fd00::1/126"
            ],
            "auto_route": true,
            "strict_route": true
        }
    ],
    "route": {
        "rules": [
            {
				"inbound": "tun-in",
                "action": "sniff"
            },
            {
              "protocol": "dns",
                "action": "hijack-dns"
            },
            {
              "port": 443,
              "network": "udp",
              "action": "reject"
            },
            {
                "ip_is_private": true,
                "outbound": "direct"
            },
            {
                "rule_set": "geosite-cn",
                "outbound": "direct"
            },
            {
                "rule_set": "geoip-cn",
                "outbound": "direct"
            },
            {
                "clash_mode": "Global",
                "outbound": "proxy"
            },
            {
                "clash_mode": "Direct",
                "outbound": "direct"
            }		
        ],
        "rule_set": [
            {
                "tag": "geosite-cn",
                "type": "remote",
                "format": "binary",
                "url": "https://cdn.jsdelivr.net/gh/MetaCubeX/meta-rules-dat@sing/geo/geosite/geolocation-cn.srs",
                "download_detour": "direct"
            },
            {
                "tag": "geoip-cn",
                "type": "remote",
                "format": "binary",
                "url": "https://cdn.jsdelivr.net/gh/MetaCubeX/meta-rules-dat@sing/geo/geoip/cn.srs",
                "download_detour": "direct"
            }
        ],
        "final": "proxy",
        "auto_detect_interface": true,
        "default_domain_resolver": {
            "server": "aliDns"
        }
    },
    "outbounds": [
    {
      "type": "vless",
      "tag": "vless-instance-20230521-2323",
      "server": "130.162.193.44",
      "server_port": 55734,
      "uuid": "8ef0cc19-be30-47a5-aedc-87d12c8a8cb4",
      "flow": "xtls-rprx-vision",
      "tls": {
        "enabled": true,
        "server_name": "www.amd.com",
        "utls": {
          "enabled": true,
          "fingerprint": "chrome"
        },
      "reality": {
          "enabled": true,
          "public_key": "diQ9hFgWl6nF7igoJnECyO4ZPgsUynmYU2-bPw99TjE",
          "short_id": "a99bb853"
        }
      }
    },
{
            "server": "130.162.193.44",
            "server_port": 8080,
            "tag": "vmess-instance-20230521-2323",
            "tls": {
                "enabled": false,
                "server_name": "www.bing.com",
                "insecure": false,
                "utls": {
                    "enabled": true,
                    "fingerprint": "chrome"
                }
            },
            "packet_encoding": "packetaddr",
            "transport": {
                "headers": {
                    "Host": [
                        "www.bing.com"
                    ]
                },
                "path": "8ef0cc19-be30-47a5-aedc-87d12c8a8cb4-vm",
                "type": "ws"
            },
            "type": "vmess",
            "security": "auto",
            "uuid": "8ef0cc19-be30-47a5-aedc-87d12c8a8cb4"
        },

    {
        "type": "hysteria2",
        "tag": "hy2-instance-20230521-2323",
        "server": "130.162.193.44",
        "server_port": 13593,
        "password": "8ef0cc19-be30-47a5-aedc-87d12c8a8cb4",
        "tls": {
            "enabled": true,
            "server_name": "www.bing.com",
            "insecure": true,
            "alpn": [
                "h3"
            ]
        }
    },
        {
            "type":"tuic",
            "tag": "tuic5-instance-20230521-2323",
            "server": "130.162.193.44",
            "server_port": 58214,
            "uuid": "8ef0cc19-be30-47a5-aedc-87d12c8a8cb4",
            "password": "8ef0cc19-be30-47a5-aedc-87d12c8a8cb4",
            "congestion_control": "bbr",
            "udp_relay_mode": "native",
            "udp_over_stream": false,
            "zero_rtt_handshake": false,
            "heartbeat": "10s",
            "tls":{
                "enabled": true,
                "server_name": "www.bing.com",
                "insecure": true,
                "alpn": [
                    "h3"
                ]
            }
        },
		{
            "type": "anytls",
            "tag": "anytls-instance-20230521-2323",
            "server": "130.162.193.44",
            "server_port": 49727,
            "password": "8ef0cc19-be30-47a5-aedc-87d12c8a8cb4",
            "idle_session_check_interval": "30s",
            "idle_session_timeout": "30s",
            "min_idle_session": 5,
            "tls": {
                "enabled": true,
                "insecure": true,
                "server_name": "www.bing.com"
              }
      },
        {
            "tag": "proxy",
            "type": "selector",
            "outbounds": [
                "auto",
                "direct",
        "vless-instance-20230521-2323",
        "vmess-instance-20230521-2323",
        "hy2-instance-20230521-2323",
        "tuic5-instance-20230521-2323",
        "anytls-instance-20230521-2323"
            ]
        },
        {
            "tag": "auto",
            "type": "urltest",
            "outbounds": [
        "vless-instance-20230521-2323",
        "vmess-instance-20230521-2323",
        "hy2-instance-20230521-2323",
        "tuic5-instance-20230521-2323",
        "anytls-instance-20230521-2323"
            ],
            "url": "http://www.gstatic.com/generate_204",
            "interval": "10m",
            "tolerance": 50
        },
        {
            "type": "direct",
            "tag": "direct"
        }
    ]
}
